{
  "name": "Splint (Steel)",
  "type": "equipment",
  "img": "icons/equipment/chest/breastplate-layered-leather-studded-black.webp",
  "effects": [],
  "flags": {},
  "system": {
    "description": {
      "value": "",
      "chat": "",
      "unidentified": ""
    },
    "source": "A5E Adventurer's Guide",
    "quantity": 1,
    "weight": 30,
    "price": {
      "value": 450,
      "denomination": "gp"
    },
    "attunement": 0,
    "equipped": false,
    "rarity": "common",
    "identified": true,
    "armor": {
      "value": null
    },
    "baseItem": "",
    "speed": {
      "value": null,
      "conditions": ""
    },
    "strength": null,
    "stealth": false,
    "proficient": true,
    "hp": {
      "value": null,
      "max": null,
      "dt": null,
      "conditions": ""
    }
  },
  "folder": "Hi0Exa3LBwLdqM1Q",
  "_id": "edwns4f8zfs8dely",
  "_key": "!items!edwns4f8zfs8dely"
}